nonebot_plugin_analysis_bilibili/ExpiringCache.py
nonebot_plugin_analysis_bilibili/__init__.py
nonebot_plugin_analysis_bilibili/analysis_bilibili.py
nonebot_plugin_analysis_bilibili/sign.py
nonebot_plugin_analysis_bilibili-2.8.1.dist-info/METADATA
nonebot_plugin_analysis_bilibili-2.8.1.dist-info/WHEEL
nonebot_plugin_analysis_bilibili-2.8.1.dist-info/RECORD
