Metadata-Version: 2.1
Name: nonebot-plugin-analysis-bilibili
Version: 2.8.1
Summary: nonebot2解析bilibili插件
Home-page: https://github.com/mengshouer/nonebot_plugin_analysis_bilibili
License: MIT
Keywords: nonebot,nonebot2,bilibili
Author: mengshouer
Requires-Python: >=3.8,<4.0
Classifier: License :: OSI Approved :: MIT License
Classifier: Programming Language :: Python :: 3
Classifier: Programming Language :: Python :: 3.8
Classifier: Programming Language :: Python :: 3.9
Classifier: Programming Language :: Python :: 3.10
Classifier: Programming Language :: Python :: 3.11
Classifier: Programming Language :: Python :: 3.12
Classifier: Programming Language :: Python :: 3.13
Requires-Dist: aiohttp (>=3.7,<4.0)
Requires-Dist: nonebot-plugin-send-anything-anywhere (>=0,<1)
Requires-Dist: nonebot2 (>=2.1.1,<3.0.0)
Project-URL: Repository, https://github.com/mengshouer/nonebot_plugin_analysis_bilibili
